Metadata-Version: 1.1
Name: dphmix
Version: 0.2.0
Summary: Unsupervised and Semi-supervised Dirichlet Process Heterogeneous Mixtures
Home-page: https://github.com/tahmidmehdi/dphmix
Author: Tahmid Mehdi
Author-email: tfmehdi@cs.toronto.edu
License: GNU GPL v3.0
Download-URL: https://github.com/tahmidmehdi/dphmix/archive/v0.2.0.tar.gz
Platform: UNKNOWN
Classifier: Intended Audience :: Science/Research
Classifier: License :: OSI Approved :: GNU General Public License v3 (GPLv3)
Classifier: Natural Language :: English
Classifier: Programming Language :: Python :: 3.7
Classifier: Topic :: Scientific/Engineering :: Artificial Intelligence
